{
  "formatVersion": 1,
  "database": {
    "version": 1,
    "identityHash": "9692507c73361b3677fb7fbbf2e1573c",
    "entities": [
      {
        "tableName": "Place",
        "createSql": "CREATE TABLE IF NOT EXISTS `${TABLE_NAME}` (`id` INTEGER PRIMARY KEY AUTOINCREMENT NOT NULL, `name` TEXT NOT NULL)",
        "fields": [
          {
            "fieldPath": "id",
            "columnName": "id",
            "affinity": "INTEGER",
            "notNull": true
          },
          {
            "fieldPath": "name",
            "columnName": "name",
            "affinity": "TEXT",
            "notNull": true
          }
        ],
        "primaryKey": {
          "autoGenerate": true,
          "columnNames": [
            "id"
          ]
        }
      },
      {
        "tableName": "ParameterEntity",
        "createSql": "CREATE TABLE IF NOT EXISTS `${TABLE_NAME}` (`key` TEXT NOT NULL, `value` TEXT NOT NULL, PRIMARY KEY(`key`))",
        "fields": [
          {
            "fieldPath": "key",
            "columnName": "key",
            "affinity": "TEXT",
            "notNull": true
          },
          {
            "fieldPath": "value",
            "columnName": "value",
            "affinity": "TEXT",
            "notNull": true
          }
        ],
        "primaryKey": {
          "autoGenerate": false,
          "columnNames": [
            "key"
          ]
        }
      },
      {
        "tableName": "ScheduleSlotEntity",
        "createSql": "CREATE TABLE IF NOT EXISTS `${TABLE_NAME}` (`placeId` INTEGER NOT NULL, `dayOfWeek` INTEGER NOT NULL, `hourOfDay` INTEGER NOT NULL, `status` TEXT NOT NULL, PRIMARY KEY(`placeId`, `dayOfWeek`, `hourOfDay`), FOREIGN KEY(`placeId`) REFERENCES `Place`(`id`) ON UPDATE NO ACTION ON DELETE CASCADE )",
        "fields": [
          {
            "fieldPath": "placeId",
            "columnName": "placeId",
            "affinity": "INTEGER",
            "notNull": true
          },
          {
            "fieldPath": "dayOfWeek",
            "columnName": "dayOfWeek",
            "affinity": "INTEGER",
            "notNull": true
          },
          {
            "fieldPath": "hourOfDay",
            "columnName": "hourOfDay",
            "affinity": "INTEGER",
            "notNull": true
          },
          {
            "fieldPath": "status",
            "columnName": "status",
            "affinity": "TEXT",
            "notNull": true
          }
        ],
        "primaryKey": {
          "autoGenerate": false,
          "columnNames": [
            "placeId",
            "dayOfWeek",
            "hourOfDay"
          ]
        },
        "foreignKeys": [
          {
            "table": "Place",
            "onDelete": "CASCADE",
            "onUpdate": "NO ACTION",
            "columns": [
              "placeId"
            ],
            "referencedColumns": [
              "id"
            ]
          }
        ]
      }
    ],
    "setupQueries": [
      "CREATE TABLE IF NOT EXISTS room_master_table (id INTEGER PRIMARY KEY,identity_hash TEXT)",
      "INSERT OR REPLACE INTO room_master_table (id,identity_hash) VALUES(42, '9692507c73361b3677fb7fbbf2e1573c')"
    ]
  }
}